socialmapper/__init__.py
socialmapper/_census.py
socialmapper/_geocoding.py
socialmapper/_osm.py
socialmapper/_visualization.py
socialmapper/api.py
"socialmapper/api.py,cover"
socialmapper/api_result_types.py
socialmapper/constants.py
socialmapper/demo.py
socialmapper/exceptions.py
socialmapper/helpers.py
socialmapper/neighbors.py
socialmapper/poi_categorization.py
socialmapper/tutorial_helper.py
socialmapper/validators.py
socialmapper/config/__init__.py
socialmapper/data/demo/README.md
socialmapper/distance/__init__.py
socialmapper/distance/engine.py
socialmapper/geocoding/__init__.py
socialmapper/geocoding/cache.py
socialmapper/geocoding/engine.py
socialmapper/geocoding/models.py
socialmapper/geocoding/providers.py
socialmapper/io/__init__.py
socialmapper/io/manager.py
socialmapper/io/readers.py
socialmapper/io/writers.py
socialmapper/isochrone/__init__.py
socialmapper/isochrone/cache.py
socialmapper/isochrone/clustering.py
socialmapper/isochrone/concurrent.py
socialmapper/isochrone/travel_modes.py
socialmapper/isochrone/backends/__init__.py
socialmapper/isochrone/backends/base.py
socialmapper/isochrone/backends/factory.py
socialmapper/isochrone/backends/networkx_backend.py
socialmapper/isochrone/backends/routing_api.py
socialmapper/performance/__init__.py
socialmapper/performance/cache.py
socialmapper/performance/config.py
socialmapper/performance/connection_pool.py
socialmapper/progress/__init__.py
socialmapper/query/__init__.py
socialmapper/query/osmnx_query.py
socialmapper/query/polygon_queries.py
socialmapper-1.1.2.data/data/socialmapper/data/demo/README.md
socialmapper-1.1.2.dist-info/METADATA
socialmapper-1.1.2.dist-info/WHEEL
socialmapper-1.1.2.dist-info/licenses/LICENSE
socialmapper-1.1.2.dist-info/RECORD
