Metadata-Version: 2.4
Name: socialmapper
Version: 1.1.2
Summary: A Python library for spatial analysis, demographic mapping, and geospatial data processing with a modern API
Project-URL: Homepage, https://github.com/mihiarc/socialmapper
Project-URL: Bug Tracker, https://github.com/mihiarc/socialmapper/issues
Author-email: mihiarc <mihiarc@example.com>
License: MIT License
License-File: LICENSE
Keywords: OpenStreetMap,census,demographics,gis,mapping
Classifier: Development Status :: 5 - Production/Stable
Classifier: Intended Audience :: Developers
Classifier: Intended Audience :: Science/Research
Classifier: License :: OSI Approved :: MIT License
Classifier: Programming Language :: Python :: 3
Classifier: Programming Language :: Python :: 3.11
Classifier: Programming Language :: Python :: 3.12
Classifier: Programming Language :: Python :: 3.13
Classifier: Topic :: Scientific/Engineering :: GIS
Requires-Python: <3.14,>=3.11
Requires-Dist: contextily>=1.6.2
Requires-Dist: cryptography>=45.0.7
Requires-Dist: diskcache>=5.6.3
Requires-Dist: folium>=0.20.0
Requires-Dist: geopandas>=1.1.0
Requires-Dist: httpx>=0.28.1
Requires-Dist: keyring>=25.6.0
Requires-Dist: mapclassify>=2.4.0
Requires-Dist: matplotlib>=3.10.3
Requires-Dist: networkx>=3.5
Requires-Dist: numba>=0.61.2
Requires-Dist: numpy<2.2,>=2.1.0
Requires-Dist: osmnx>=2.0.3
Requires-Dist: overpy>=0.7
Requires-Dist: pandas>=2.3.0
Requires-Dist: polars>=0.20.0
Requires-Dist: psutil>=7.0.0
Requires-Dist: pyarrow>=12.0.0
Requires-Dist: pydantic>=2.11.7
Requires-Dist: pyogrio>=0.11.0
Requires-Dist: pyproj>=3.7.1
Requires-Dist: python-dotenv>=1.1.0
Requires-Dist: pyyaml>=6.0
Requires-Dist: requests>=2.32.4
Requires-Dist: rich>=14.0.0
Requires-Dist: scikit-learn>=1.7.0
Requires-Dist: shapely>=2.0.0
Requires-Dist: tqdm>=4.67.1
Provides-Extra: dev
Requires-Dist: mkdocs-material-extensions>=1.3.1; extra == 'dev'
Requires-Dist: mkdocs>=1.6.1; extra == 'dev'
Requires-Dist: pytest>=8.4.1; extra == 'dev'
Requires-Dist: ruff>=0.12.0; extra == 'dev'
Requires-Dist: ty>=0.0.1a10; extra == 'dev'
Provides-Extra: routing
Requires-Dist: routingpy>=1.3.0; extra == 'routing'
